intocpsdtp/Experiments.py
intocpsdtp/__init__.py
into_cps_dtp-0.0.2.dist-info/LICENSE.md
into_cps_dtp-0.0.2.dist-info/METADATA
into_cps_dtp-0.0.2.dist-info/WHEEL
into_cps_dtp-0.0.2.dist-info/top_level.txt
into_cps_dtp-0.0.2.dist-info/RECORD
