Metadata-Version: 2.1
Name: into-cps-dtp
Version: 0.0.2
Summary: A utility to show basic ISO 1178-10 XML data
Home-page: https://github.com/INTO-CPS-Association/into-cps-dtp
Author: INTO-CPS
License: INTO-CPS
Project-URL: Bug Reports, https://github.com/INTO-CPS-Association/into-cps-dtp/issues
Project-URL: Funding, https://github.com/INTO-CPS-Association/into-cps-dtp
Project-URL: Source, https://github.com/INTO-CPS-Association/into-cps-dtp
Keywords: digitaltwin,co-simulation
Platform: UNKNOWN
Classifier: Development Status :: 3 - Alpha
Classifier: Intended Audience :: Developers
Classifier: Topic :: Software Development :: Build Tools
Classifier: Programming Language :: Python :: 3
Classifier: Programming Language :: Python :: 3.6
Classifier: Programming Language :: Python :: 3.7
Classifier: Programming Language :: Python :: 3.8
Classifier: Programming Language :: Python :: 3.9
Classifier: Programming Language :: Python :: 3 :: Only
Requires-Python: >=3.7, <4
License-File: LICENSE.md
Provides-Extra: dev
Requires-Dist: check-manifest ; extra == 'dev'
Provides-Extra: tests
Requires-Dist: coverage ; extra == 'tests'
